aa_stripe/__init__.py
aa_stripe/admin.py
aa_stripe/api.py
aa_stripe/api_urls.py
aa_stripe/exceptions.py
aa_stripe/forms.py
aa_stripe/models.py
aa_stripe/serializers.py
aa_stripe/settings.py
aa_stripe/signals.py
aa_stripe/utils.py
aa_stripe/management/__init__.py
aa_stripe/management/commands/__init__.py
aa_stripe/management/commands/charge_stripe.py
aa_stripe/management/commands/check_pending_webhooks.py
aa_stripe/management/commands/end_subscriptions.py
aa_stripe/management/commands/refresh_coupons.py
aa_stripe/management/commands/refresh_customers.py
aa_stripe/migrations/0001_initial.py
aa_stripe/migrations/0002_auto_20170607_0714.py
aa_stripe/migrations/0003_auto_20170608_1103.py
aa_stripe/migrations/0004_auto_20170613_0419.py
aa_stripe/migrations/0005_auto_20170613_0614.py
aa_stripe/migrations/0006_subscription_end_cancel.py
aa_stripe/migrations/0007_auto_20170630_0557.py
aa_stripe/migrations/0008_auto_20170630_0734.py
aa_stripe/migrations/0009_auto_20170725_1205.py
aa_stripe/migrations/0010_auto_20170822_1004.py
aa_stripe/migrations/0011_auto_20170907_1201.py
aa_stripe/migrations/0012_auto_20170908_1150.py
aa_stripe/migrations/0013_stripesubscription_at_period_end.py
aa_stripe/migrations/0014_stripecharge_charge_attempt_failed.py
aa_stripe/migrations/0015_auto_20170925_0838.py
aa_stripe/migrations/0016_stripecharge_is_refunded.py
aa_stripe/migrations/0017_stripecharge_manual_charge.py
aa_stripe/migrations/0018_stripecustomer_sources.py
aa_stripe/migrations/0019_stripecustomer_default_source.py
aa_stripe/migrations/0020_stripecharge_statement_descriptor.py
aa_stripe/migrations/0021_auto_20190906_1623.py
aa_stripe/migrations/0022_stripecharge_amount_refunded.py
aa_stripe/migrations/__init__.py
aa_stripe-0.13.0.dist-info/AUTHORS
aa_stripe-0.13.0.dist-info/LICENSE
aa_stripe-0.13.0.dist-info/METADATA
aa_stripe-0.13.0.dist-info/WHEEL
aa_stripe-0.13.0.dist-info/top_level.txt
aa_stripe-0.13.0.dist-info/RECORD
