Metadata-Version: 2.1
Name: aa-stripe
Version: 0.13.0
Summary: Stripe integration for Django-based projects
Home-page: https://github.com/HealthByRo/aa-stripe
Author: Remigiusz Dymecki
Author-email: remi@ro.co
License: MIT
Platform: UNKNOWN
Classifier: Development Status :: 4 - Beta
Classifier: Environment :: Web Environment
Classifier: Framework :: Django
Classifier: Intended Audience :: Developers
Classifier: Operating System :: OS Independent
Classifier: Programming Language :: Python
Classifier: Programming Language :: Python :: 3.9
Classifier: Programming Language :: Python :: 3.10
Classifier: Programming Language :: Python :: 3.11
Classifier: Topic :: Internet :: WWW/HTTP
License-File: LICENSE
License-File: AUTHORS
Requires-Dist: django-extensions >=2.1.3
Requires-Dist: stripe <3.0.0,>=2.35.1
Requires-Dist: djangorestframework >=3.6.0
Requires-Dist: simplejson >=3.10.0
Requires-Dist: django <4.3,>=2.2.14
